cdk_cloudwatch_auto_retention/__init__.py
cdk_cloudwatch_auto_retention/py.typed
cdk_cloudwatch_auto_retention/_jsii/__init__.py
cdk_cloudwatch_auto_retention/_jsii/cloudwatch-auto-retention@1.0.0.jsii.tgz
cloudwatch_auto_retention-1.0.0.dist-info/LICENSE
cloudwatch_auto_retention-1.0.0.dist-info/METADATA
cloudwatch_auto_retention-1.0.0.dist-info/WHEEL
cloudwatch_auto_retention-1.0.0.dist-info/top_level.txt
cloudwatch_auto_retention-1.0.0.dist-info/RECORD
