Metadata-Version: 2.1
Name: cloudwatch-auto-retention
Version: 1.0.0
Summary: CloudWatch Auto Retention is a construct that creates a Lambda with a cronjob that checks whether CloudWatch loggroups are set to never-expire. If so, the construct sets it to one month.
Home-page: https://github.com/stroobants-dev/cloudwatch-auto-retention
Author: Tom Stroobants<tom@stroobants.dev>
License: Apache-2.0
Project-URL: Source, https://github.com/stroobants-dev/cloudwatch-auto-retention
Platform: UNKNOWN
Classifier: Intended Audience :: Developers
Classifier: Operating System :: OS Independent
Classifier: Programming Language :: JavaScript
Classifier: Programming Language :: Python :: 3 :: Only
Classifier: Programming Language :: Python :: 3.6
Classifier: Programming Language :: Python :: 3.7
Classifier: Programming Language :: Python :: 3.8
Classifier: Programming Language :: Python :: 3.9
Classifier: Typing :: Typed
Classifier: Development Status :: 5 - Production/Stable
Classifier: License :: OSI Approved
Requires-Python: >=3.6
License-File: LICENSE
Requires-Dist: aws-cdk-lib (<3.0.0,>=2.1.0)
Requires-Dist: constructs (<11.0.0,>=10.0.5)
Requires-Dist: jsii (<2.0.0,>=1.47.0)
Requires-Dist: publication (>=0.0.3)
